pixelyodi/__init__.py
pixelyodi/main.py
yodinews-0.3.2.dist-info/LICENSE
yodinews-0.3.2.dist-info/METADATA
yodinews-0.3.2.dist-info/WHEEL
yodinews-0.3.2.dist-info/top_level.txt
yodinews-0.3.2.dist-info/RECORD
