Metadata-Version: 2.1
Name: yodinews
Version: 0.3.2
License-File: LICENSE
